{
    "emacs-overlay": {
        "branch": "master",
        "description": "Bleeding edge emacs overlay [maintainer=@adisbladis] ",
        "homepage": "",
        "owner": "nix-community",
        "repo": "emacs-overlay",
        "rev": "d43b200ed5675bf912440975435dd7a7363f9481",
        "sha256": "11vwpf2kgwpsy3hw4f02mm93cn8mrkd4b5irkidvfvvxwlvw5zrv",
        "type": "tarball",
        "url": "https://github.com/nix-community/emacs-overlay/archive/d43b200ed5675bf912440975435dd7a7363f9481.tar.gz",
        "url_template": "https://github.com/<owner>/<repo>/archive/<rev>.tar.gz"
    },
    "gitignore": {
        "branch": "master",
        "description": "Nix function for filtering local git sources",
        "homepage": "",
        "owner": "hercules-ci",
        "repo": "gitignore",
        "rev": "bff2832ec341cf30acb3a4d3e2e7f1f7b590116a",
        "sha256": "0va0janxvmilm67nbl81gdbpppal4aprxzb25gp9pqvf76ahxsci",
        "type": "tarball",
        "url": "https://github.com/hercules-ci/gitignore/archive/bff2832ec341cf30acb3a4d3e2e7f1f7b590116a.tar.gz",
        "url_template": "https://github.com/<owner>/<repo>/archive/<rev>.tar.gz"
    },
    "home-manager": {
        "branch": "master",
        "description": "Manage a user environment using Nix",
        "homepage": "https://nix-community.github.io/home-manager/",
        "owner": "nix-community",
        "repo": "home-manager",
        "rev": "8eb7c009f09f1f7b1ec151e5d537104acf42213a",
        "sha256": "1j8nv6y5r9gsp6ws1bqzbqlz444qd8lz1xm848ii8ycimw9b0icr",
        "type": "tarball",
        "url": "https://github.com/nix-community/home-manager/archive/8eb7c009f09f1f7b1ec151e5d537104acf42213a.tar.gz",
        "url_template": "https://github.com/<owner>/<repo>/archive/<rev>.tar.gz"
    },
    "home-manager-stable": {
        "branch": "release-21.11",
        "description": "Manage a user environment using Nix",
        "homepage": "https://nix-community.github.io/home-manager/",
        "owner": "nix-community",
        "repo": "home-manager",
        "rev": "a8d00f5c038cf7ec54e7dac9c57b171c1217f008",
        "sha256": "1ix6cknhlrwpawlakrsd3616rgy1calnds2h6wfqrv6cfdwsyzzc",
        "type": "tarball",
        "url": "https://github.com/nix-community/home-manager/archive/a8d00f5c038cf7ec54e7dac9c57b171c1217f008.tar.gz",
        "url_template": "https://github.com/<owner>/<repo>/archive/<rev>.tar.gz"
    },
    "niv": {
        "branch": "master",
        "description": "Easy dependency management for Nix projects",
        "homepage": "https://github.com/nmattia/niv",
        "owner": "nmattia",
        "repo": "niv",
        "rev": "9cb7ef336bb71fd1ca84fc7f2dff15ef4b033f2a",
        "sha256": "1ajyqr8zka1zlb25jx1v4xys3zqmdy3prbm1vxlid6ah27a8qnzh",
        "type": "tarball",
        "url": "https://github.com/nmattia/niv/archive/9cb7ef336bb71fd1ca84fc7f2dff15ef4b033f2a.tar.gz",
        "url_template": "https://github.com/<owner>/<repo>/archive/<rev>.tar.gz"
    },
    "nixos": {
        "branch": "nixos-21.11",
        "description": "A read-only mirror of NixOS/nixpkgs tracking the released channels. Send issues and PRs to",
        "homepage": "https://github.com/NixOS/nixpkgs",
        "owner": "NixOS",
        "repo": "nixpkgs",
        "rev": "0f85665118d850aae5164d385d24783d0b16cf1b",
        "sha256": "1x60c4s885zlqm1ffvjj09mjq078rqgcd08l85004cijfsqld263",
        "type": "tarball",
        "url": "https://github.com/NixOS/nixpkgs/archive/0f85665118d850aae5164d385d24783d0b16cf1b.tar.gz",
        "url_template": "https://github.com/<owner>/<repo>/archive/<rev>.tar.gz"
    },
    "nixos-hardware": {
        "branch": "master",
        "description": "A collection of NixOS modules covering hardware quirks.",
        "homepage": "",
        "owner": "NixOS",
        "repo": "nixos-hardware",
        "rev": "816a935bf5aa5f77cb1f03ebfe20ab13b112d0f1",
        "sha256": "1dldbr0ikwb28ramzncriylfr8v6chf5wsadm844wx3487hx4sxr",
        "type": "tarball",
        "url": "https://github.com/NixOS/nixos-hardware/archive/816a935bf5aa5f77cb1f03ebfe20ab13b112d0f1.tar.gz",
        "url_template": "https://github.com/<owner>/<repo>/archive/<rev>.tar.gz"
    },
    "nixos-unstable": {
        "branch": "nixos-unstable",
        "description": "A read-only mirror of NixOS/nixpkgs tracking the released channels. Send issues and PRs to",
        "homepage": "https://github.com/NixOS/nixpkgs",
        "owner": "NixOS",
        "repo": "nixpkgs",
        "rev": "73ad5f9e147c0d2a2061f1d4bd91e05078dc0b58",
        "sha256": "01j7nhxbb2kjw38yk4hkjkkbmz50g3br7fgvad6b1cjpdvfsllds",
        "type": "tarball",
        "url": "https://github.com/NixOS/nixpkgs/archive/73ad5f9e147c0d2a2061f1d4bd91e05078dc0b58.tar.gz",
        "url_template": "https://github.com/<owner>/<repo>/archive/<rev>.tar.gz"
    },
    "nixpkgs": {
        "branch": "nixpkgs-unstable",
        "description": "A read-only mirror of NixOS/nixpkgs tracking the released channels. Send issues and PRs to",
        "homepage": "https://github.com/NixOS/nixpkgs",
        "owner": "NixOS",
        "repo": "nixpkgs",
        "rev": "be872a7453a176df625c12190b8a6c10f6b21647",
        "sha256": "1hnwh2w5rhxgbp6c8illcrzh85ky81pyqx9309bkgpivyzjf2nba",
        "type": "tarball",
        "url": "https://github.com/NixOS/nixpkgs/archive/be872a7453a176df625c12190b8a6c10f6b21647.tar.gz",
        "url_template": "https://github.com/<owner>/<repo>/archive/<rev>.tar.gz"
    },
    "sops-nix": {
        "branch": "master",
        "description": "Atomic secret provisioning for NixOS based on sops",
        "homepage": "",
        "owner": "Mic92",
        "repo": "sops-nix",
        "rev": "c01f48b055ac776f9831c9d4a0fff83e3b74dbe3",
        "sha256": "0aqhh2c8hnsm5jr7jvajvcsc2l90iv33d11nf8jk3ybxm0qxzhb6",
        "type": "tarball",
        "url": "https://github.com/Mic92/sops-nix/archive/c01f48b055ac776f9831c9d4a0fff83e3b74dbe3.tar.gz",
        "url_template": "https://github.com/<owner>/<repo>/archive/<rev>.tar.gz"
    }
}
